muldoon/__init__.py
muldoon/met_timeseries.py
muldoon/read_data.py
muldoon/utils.py
muldoon-1.3.10.dist-info/licenses/LICENSE
tests/__init__.py
tests/test_muldoon.py
tests/test_read_data.py
tests/test_utils.py
tests/test_wind_speed.py
muldoon-1.3.10.dist-info/METADATA
muldoon-1.3.10.dist-info/WHEEL
muldoon-1.3.10.dist-info/top_level.txt
muldoon-1.3.10.dist-info/RECORD
